MANIFEST.in
setup.cfg
setup.py
consort/__init__.py
consort/_version.py
consort.egg-info/PKG-INFO
consort.egg-info/SOURCES.txt
consort.egg-info/dependency_links.txt
consort.egg-info/not-zip-safe
consort.egg-info/requires.txt
consort.egg-info/top_level.txt
consort/stylesheets/consort-header.ily
consort/stylesheets/consort-layout-annotations.ily
consort/stylesheets/consort-layout-brass.ily
consort/stylesheets/consort-layout-electronics.ily
consort/stylesheets/consort-layout-keyboards.ily
consort/stylesheets/consort-layout-percussion.ily
consort/stylesheets/consort-layout-strings.ily
consort/stylesheets/consort-layout-winds.ily
consort/stylesheets/consort-layout.ily
consort/stylesheets/consort-paper.ily
consort/stylesheets/stylesheet.ily
consort/tools/AbsolutePitchHandler.py
consort/tools/AfterGraceSelectorCallback.py
consort/tools/AttachmentExpression.py
consort/tools/AttachmentHandler.py
consort/tools/AttackPointSignature.py
consort/tools/BoundaryTimespanMaker.py
consort/tools/CascadingTimespanMaker.py
consort/tools/ChordExpression.py
consort/tools/ChordSpecifier.py
consort/tools/ClefSpanner.py
consort/tools/ClefSpannerExpression.py
consort/tools/Color.py
consort/tools/ColorBracket.py
consort/tools/ComplexPianoPedalSpanner.py
consort/tools/ComplexTextSpanner.py
consort/tools/CompositeMusicSpecifier.py
consort/tools/CompositeRhythmMaker.py
consort/tools/ConsortTrillSpanner.py
consort/tools/Cursor.py
consort/tools/DependentTimespanMaker.py
consort/tools/Dynamic.py
consort/tools/DynamicExpression.py
consort/tools/FloodedTimespanMaker.py
consort/tools/Glissando.py
consort/tools/GraceHandler.py
consort/tools/HarmonicExpression.py
consort/tools/HashCachingObject.py
consort/tools/Instrument.py
consort/tools/KeyClickExpression.py
consort/tools/KeyClusterExpression.py
consort/tools/LeafExpression.py
consort/tools/LogicalTieExpression.py
consort/tools/MusicSetting.py
consort/tools/MusicSpecifier.py
consort/tools/MusicSpecifierSequence.py
consort/tools/OctavationExpression.py
consort/tools/PackageGitCommitToken.py
consort/tools/PerformedTimespan.py
consort/tools/PhrasedSelectorCallback.py
consort/tools/PitchClassPitchHandler.py
consort/tools/PitchHandler.py
