Metadata-Version: 1.0
Name: consort
Version: 0.2
Summary: High-level tools for formalized score control in Abjad.
Home-page: https://github.com/josiah-wolf-oberholtzer/consort
Author: Josiah Wolf Oberholtzer
Author-email: josiah.oberholtzer@gmail.com
License: UNKNOWN
Platform: UNKNOWN
